Metadata-Version: 2.4
Name: pypgx
Version: 0.26.0
Summary: A Python package for pharmacogenomics (PGx) research
Home-page: https://github.com/sbslee/pypgx
Author: Seung-been "Steven" Lee
Author-email: sbstevenlee@gmail.com
License: MIT
Classifier: Programming Language :: Python :: 3
Classifier: License :: OSI Approved :: MIT License
License-File: LICENSE
Requires-Dist: fuc
Requires-Dist: scikit-learn
Dynamic: author
Dynamic: author-email
Dynamic: classifier
Dynamic: description
Dynamic: description-content-type
Dynamic: home-page
Dynamic: license
Dynamic: license-file
Dynamic: requires-dist
Dynamic: summary
